[
    {
          "id": 1,
          "characterName": "Homer Simpson",
          "characterImage": "HomerSimpson.png"
    },
    {
          "id": 2,
          "characterName": "Bart Simpson",
          "characterImage": "BartSimpson.png"
    },
    {
          "id": 3,
          "characterName": "Marge Simpson",
          "characterImage": "MargeSimpson.png"
    },
    {
          "id": 4,
          "characterName": "Lisa Simpson",
          "characterImage": "LisaSimpson.png"
    },
    {
          "id": 5,
          "characterName": "Mr. Burns",
          "characterImage": "MrBurns.png"
    },
    {
          "id": 6,
          "characterName": "Apu Nahasapeemapetilon",
          "characterImage": "ApuNahasapeemapetilon.png"
    },
    {
          "id": 7,
          "characterName": "Ned Flanders",
          "characterImage": "NedFlanders.png"
    },
    {
          "id": 8,
          "characterName": "Milhouse Van Houten",
          "characterImage": "MilhouseVanHouten.png"
    },
    {
          "id": 9,
          "characterName": "Moe Szyslack",
          "characterImage": "MoeSzyslack.png"
    },
    {
          "id": 10,
          "characterName": "Nelson Muntz",
          "characterImage": "NelsonMuntz.png"
    },
    {
          "id": 11,
          "characterName": "Krusty the Clown",
          "characterImage": "KrustytheClown.png"
    },
    {
          "id": 12,
          "characterName": "Edna Krabappel",
          "characterImage": "EdnaKrabappel.png"
    }, 
    {
        "id": 13,
        "characterName": "Waylon Smithers",
        "characterImage": "WaylonSmithers.png"
  },
  {
        "id": 14,
        "characterName": "Barney Gumble",
        "characterImage": "BarneyGumble.png"
  },
  {
        "id": 15,
        "characterName": "Ralph Wiggum",
        "characterImage": "RalphWiggum.png"
  },
  {
        "id": 16,
        "characterName": "Principal Skinner",
        "characterImage": "PrincipalSkinner.png"
  },
  {
        "id": 17,
        "characterName": "Grandpa Simpson",
        "characterImage": "GrandpaSimpson.png"
  },
  {
        "id": 18,
        "characterName": "Comic Book Guy",
        "characterImage": "ComicBookGuy.png"
  },
  {
        "id": 19,
        "characterName": "Fat Tony",
        "characterImage": "FatTony.png"
  },
  {
        "id": 20,
        "characterName": "Martin Prince",
        "characterImage": "MartinPrince.png"
  },
  {
        "id": 21,
        "characterName": "Santas Little Helper",
        "characterImage": "SantasLittleHelper.png"
  },
  {
        "id": 22,
        "characterName": "Grounds Keeper Willie",
        "characterImage": "GroundsKeeperWillie.png"
  },
  {
        "id": 23,
        "characterName": "Troy McClure",
        "characterImage": "TroyMcClure.png"
  },
  {
        "id": 24,
        "characterName": "Lenny Leonard",
        "characterImage": "LennyLeonard.png"
  },
{
      "id": 25,
      "characterName": "Hans Moleman",
      "characterImage": "HansMoleman.png"
},
{
      "id": 26,
      "characterName": "Herbert Powell",
      "characterImage": "HerbertPowell.png"
},
{
      "id": 27,
      "characterName": "Chief Wiggum",
      "characterImage": "ChiefWiggum.png"
},
{
      "id": 28,
      "characterName": "Patty Bouvier",
      "characterImage": "PattyBouvier.png"
},
{
      "id": 29,
      "characterName": "Dan Gillick",
      "characterImage": "DanGillick.png"
},
{
      "id": 30,
      "characterName": "Dr. Hibbert",
      "characterImage": "DrHibbert.png"
},
{
      "id": 31,
      "characterName": "Maude Flanders",
      "characterImage": "MaudeFlanders.png"
},
{ 
      "id": 32,
      "characterName": "Side Show Mel",
      "characterImage": "SideShowMel.png"
}
]